azure/developer/devcenter/__init__.py
azure/developer/devcenter/_client.py
azure/developer/devcenter/_configuration.py
azure/developer/devcenter/_model_base.py
azure/developer/devcenter/_patch.py
azure/developer/devcenter/_serialization.py
azure/developer/devcenter/_vendor.py
azure/developer/devcenter/_version.py
azure/developer/devcenter/py.typed
azure/developer/devcenter/_operations/__init__.py
azure/developer/devcenter/_operations/_operations.py
azure/developer/devcenter/_operations/_patch.py
azure/developer/devcenter/aio/__init__.py
azure/developer/devcenter/aio/_client.py
azure/developer/devcenter/aio/_configuration.py
azure/developer/devcenter/aio/_patch.py
azure/developer/devcenter/aio/_vendor.py
azure/developer/devcenter/aio/_operations/__init__.py
azure/developer/devcenter/aio/_operations/_operations.py
azure/developer/devcenter/aio/_operations/_patch.py
azure/developer/devcenter/models/__init__.py
azure/developer/devcenter/models/_enums.py
azure/developer/devcenter/models/_models.py
azure/developer/devcenter/models/_patch.py
azure_developer_devcenter-1.0.0.dist-info/LICENSE
azure_developer_devcenter-1.0.0.dist-info/METADATA
azure_developer_devcenter-1.0.0.dist-info/WHEEL
azure_developer_devcenter-1.0.0.dist-info/top_level.txt
azure_developer_devcenter-1.0.0.dist-info/RECORD
